ai_engine_new/__init__.py
ai_engine_new/base_model/__init__.py
ai_engine_new/base_model/dream.py
ai_engine_new/base_model/kandinsky.py
ai_engine_new/kandinsky/__init__.py
ai_engine_new/kandinsky/async_kandinsky.py
ai_engine_new/kandinsky/data.py
ai_engine_new/kandinsky/kandinsky.py
ai_engine_new/kandinsky/test_kandinsky.py
ai_engine_new/models/Dream.py
ai_engine_new/models/Kandinsky.py
ai_engine_new/models/__init__.py
ai_engine_new/wombo/__init__.py
ai_engine_new/wombo/adream.py
ai_engine_new/wombo/dream.py
ai_engine_new/wombo/test_wombo.py
ai_engine_new/wombo/urls.py
ai_engine_new-0.1.12.dist-info/METADATA
ai_engine_new-0.1.12.dist-info/WHEEL
ai_engine_new-0.1.12.dist-info/RECORD
