Metadata-Version: 2.1
Name: ai_engine_new
Version: 0.1.12
Summary: Generate images ai, revers enginering
Home-page: https://cumproject.ru/
License: MIT
Author: Aleksey Baev
Author-email: baev@cumproject.ru
Requires-Python: >=3.8.0
Classifier: License :: OSI Approved :: MIT License
Classifier: Programming Language :: Python :: 3
Classifier: Programming Language :: Python :: 3.8
Classifier: Programming Language :: Python :: 3.9
Classifier: Programming Language :: Python :: 3.10
Classifier: Programming Language :: Python :: 3.11
Provides-Extra: testing
Requires-Dist: httpx (>=0.25.0,<0.26.0)
Requires-Dist: pydantic (>=1.10.12,<=2.3.0)
Requires-Dist: pytest (>=7.4.2,<8.0.0) ; extra == "testing"
Project-URL: Repository, https://github.com/pokedim13/images_ai
